{
    "ingredientes": [
        {
            "id": 0,
            "nombre": "Harina de Trigo 0000",
            "stockMinimoInsumo": 100000,
            "unidadMedida": "gr",
            "cantidadActual": 150000,
            "rubroIngrediente": "Harinas",
            "estado": true,
            "costoPorUnidad": 0.2
        },
        {
            "id": 1,
            "nombre": "Salsa de Tomate",
            "stockMinimoInsumo": 25000,
            "unidadMedida": "ml",
            "cantidadActual": 50000,
            "rubroIngrediente": "Vegetales",
            "estado": true,
            "costoPorUnidad": 0.5
        },
        {
            "id": 2,
            "nombre": "Queso Cremoso",
            "stockMinimoInsumo": 20000,
            "unidadMedida": "gr",
            "cantidadActual": 40000,
            "rubroIngrediente": "Lácteos",
            "estado": false,
            "costoPorUnidad": 2.3
        },
        {
            "id": 3,
            "nombre": "Jamón Cocido",
            "stockMinimoInsumo": 20000,
            "unidadMedida": "gr",
            "cantidadActual": 15000,
            "rubroIngrediente": "Embutidos",
            "estado": true,
            "costoPorUnidad": 3
        },
        {
            "id": 4,
            "nombre": "Carne Molida",
            "stockMinimoInsumo": 20000,
            "unidadMedida": "gr",
            "cantidadActual": 50000,
            "rubroIngrediente": "Carne",
            "estado": true,
            "costoPorUnidad": 1.2
        },
        {
            "id": 5,
            "nombre": "Tomate",
            "stockMinimoInsumo": 20000,
            "unidadMedida": "gr",
            "cantidadActual": 21000,
            "rubroIngrediente": "Vegetales",
            "estado": true,
            "costoPorUnidad": 0.7
        },
        {
            "id": 6,
            "nombre": "Lechuga",
            "stockMinimoInsumo": 5000,
            "unidadMedida": "gr",
            "cantidadActual": 0,
            "rubroIngrediente": "Vegetales",
            "estado": false,
            "costoPorUnidad": 0.7
        },
        {
            "id": 7,
            "nombre": "Huevos",
            "stockMinimoInsumo": 100,
            "unidadMedida": "unidad",
            "cantidadActual": 80,
            "rubroIngrediente": "De Origen Animal",
            "estado": true,
            "costoPorUnidad": 80
        },
        {
            "id": 8,
            "nombre": "Cebolla",
            "stockMinimoInsumo": 20000,
            "unidadMedida": "gr",
            "cantidadActual": 45000,
            "rubroIngrediente": "Vegetales",
            "estado": true,
            "costoPorUnidad": 0.17
        },
        {
            "id": 9,
            "nombre": "Pan para Panchos",
            "stockMinimoInsumo": 48,
            "unidadMedida": "unidad",
            "cantidadActual": 60,
            "rubroIngrediente": "Pan",
            "estado": false,
            "costoPorUnidad": 45
        },
        {
            "id": 10,
            "nombre": "Salchicha",
            "stockMinimoInsumo": 80,
            "unidadMedida": "unidad",
            "cantidadActual": 100,
            "rubroIngrediente": "Embutidos",
            "estado": true,
            "costoPorUnidad": 52
        },
        {
            "id": 11,
            "nombre": "Papa",
            "stockMinimoInsumo": 10000,
            "unidadMedida": "gr",
            "cantidadActual": 9000,
            "rubroIngrediente": "Vegetales",
            "estado": true,
            "costoPorUnidad": 0.5
        },
        {
            "id": 12,
            "nombre": "Queso Calabrese",
            "stockMinimoInsumo": 15000,
            "unidadMedida": "gr",
            "cantidadActual": 30000,
            "rubroIngrediente": "Lácteos",
            "estado": false,
            "costoPorUnidad": 3
        },
        {
            "id": 13,
            "nombre": "Queso Provolone",
            "stockMinimoInsumo": 10000,
            "unidadMedida": "gr",
            "cantidadActual": 0,
            "rubroIngrediente": "Lácteos",
            "estado": true,
            "costoPorUnidad": 4.3
        },
        {
            "id": 14,
            "nombre": "Lluvia de Papas",
            "stockMinimoInsumo": 3000,
            "unidadMedida": "gr",
            "cantidadActual": 5000,
            "rubroIngrediente": "Vegetales",
            "estado": true,
            "costoPorUnidad": 3
        },
        {
            "id": 15,
            "nombre": "Ají Molido",
            "stockMinimoInsumo": 1000,
            "unidadMedida": "gr",
            "cantidadActual": 1500,
            "rubroIngrediente": "Especias",
            "estado": true,
            "costoPorUnidad": 5
        },
        {
            "id": 16,
            "nombre": "Calabrese",
            "stockMinimoInsumo": 3000,
            "unidadMedida": "gr",
            "cantidadActual": 6000,
            "rubroIngrediente": "Embutidos",
            "estado": true,
            "costoPorUnidad": 1.8
        }
    ]
}